trie_larry/__init__.py
trie_larry/trie.py
trie_larry-1.0.1.dist-info/METADATA
trie_larry-1.0.1.dist-info/WHEEL
trie_larry-1.0.1.dist-info/top_level.txt
trie_larry-1.0.1.dist-info/RECORD
