Metadata-Version: 2.1
Name: trie-larry
Version: 1.0.1
Summary: trie.py: a efficient package for search words using trie tree.
Home-page: http://webpy.org/
Author: Larry King
Author-email: 1412857955@qq.com
Maintainer: Scut Emos
Maintainer-email: emos@scut.edu.cn
License: Public domain
Platform: any
